amoo_sajjad_cow/__init__.py
amoo_sajjad_cow/amoo_sajjad_cow.py
amoo_sajjad_cow-1.0.0.dist-info/METADATA
amoo_sajjad_cow-1.0.0.dist-info/WHEEL
amoo_sajjad_cow-1.0.0.dist-info/top_level.txt
amoo_sajjad_cow-1.0.0.dist-info/RECORD
