Metadata-Version: 2.1
Name: amoo_sajjad_cow
Version: 1.0.0
Summary: A test package for pydeploy students
Author: Sajjad Aemmi
Author-email: sajjadaemmi@gmail.com
